{
  "planets": [
    {
      "name": "planet1",
      "mass": 7000000000000000.0,
      "radius": 6,
      "isAffectedByGravity": false,
      "posX": 400,
      "posY": 100,
      "velX": 0,
      "velY": 0,
      "img_path": "/img/kanye.jpg"
    }
  ],
  "playerObject": [
    {
      "name": "playerObj",
      "mass": 4,
      "radius": 20,
      "isAffectedByGravity": true,
      "posX": 50,
      "posY": 50,
      "velX": 0,
      "velY": 0,
      "img_path": "/img/kanye.jpg"
    },
    {
      "name": "playerObj1",
      "mass": 4,
      "radius": 20,
      "isAffectedByGravity": true,
      "posX": 70,
      "posY": 50,
      "velX": 0,
      "velY": 0,
      "img_path": "/img/kanye.jpg"
    }
  ],
  "target": [
    {
      "name": "target1",
      "mass": 786000000000000,
      "radius": 20,
      "isAffectedByGravity": false,
      "posX": 150,
      "posY": 0,
      "velX": 0,
      "velY": 0,
      "img_path": "/img/kanye.jpg"
    },
    {
      "name": "target2",
      "mass": 786000000000000,
      "radius": 20,
      "isAffectedByGravity": false,
      "posX": 100,
      "posY": 250,
      "velX": 0,
      "velY": 0,
      "img_path": "/img/kanye.jpg"
    }
  ]
}