{
  "planets": [
    {
      "name": "planet1",
      "mass": 10000,
      "radius": 1,
      "isAffectedByGravity": true,
      "posX": 10000,
      "posY": 1000,
      "velX": 20,
      "velY": 20,
      "img_path": "/test/hest/best/yes-t"
    },
    {
      "name": "planet2",
      "mass": 500,
      "radius": 1,
      "isAffectedByGravity": true,
      "posX": 1000,
      "posY": 1000,
      "velX": 20,
      "velY": 20,
      "img_path": ""
    }
  ],
  "playerObject": [
    {
      "name": "playerObj",
      "mass": 500,
      "radius": 20,
      "isAffectedByGravity": true,
      "posX": 50,
      "posY": 50,
      "velX": 0,
      "velY": 0,
      "img_path": ""
    }
  ],
  "target": [
  {
    "name": "target1",
    "mass": null,
    "radius": 64,
    "isAffectedByGravity": false,
    "posX": 100,
    "posY": 100,
    "velX": 0,
    "velY": 0,
    "img_path": ""
  }
]
}